iremover/__init__.py
iremover/base_session.py
iremover/bg.py
iremover/cli.py
iremover/cloth_session.py
iremover/session.py
iremover/simple_session.py
iremover/version.py
iremover-1.0.1.dist-info/LICENSE
iremover-1.0.1.dist-info/METADATA
iremover-1.0.1.dist-info/WHEEL
iremover-1.0.1.dist-info/entry_points.txt
iremover-1.0.1.dist-info/top_level.txt
iremover-1.0.1.dist-info/zip-safe
iremover-1.0.1.dist-info/RECORD
