Metadata-Version: 2.1
Name: iremover
Version: 1.0.1
Summary: Python 3 library. Image background remover.
Home-page: https://github.com/pchchv/iremover
Author: Evgenii Pochechuev
Author-email: ipchchv@gmail.com
License: Apache-2.0 license
Project-URL: Bug Reports, https://github.com/pchchv/iremover/issues
Project-URL: Read the Docs, https://github.com/pchchv/iremover/docs
Keywords: remove,background
Classifier: Environment :: Console
Classifier: License :: OSI Approved :: Apache Software License
Classifier: Topic :: Scientific/Engineering
Classifier: Topic :: Scientific/Engineering :: Mathematics
Classifier: Topic :: Scientific/Engineering :: Artificial Intelligence
Classifier: Topic :: Software Development
Classifier: Topic :: Software Development :: Libraries
Classifier: Topic :: Software Development :: Libraries :: Python Modules
Classifier: Programming Language :: Python
Classifier: Programming Language :: Python :: 3 :: Only
Classifier: Programming Language :: Python :: 3.8
Classifier: Programming Language :: Python :: 3.9
Classifier: Programming Language :: Python :: 3.10
Requires-Python: >=3.7
License-File: LICENSE
Requires-Dist: aiohttp (~=3.8.4)
Requires-Dist: asyncer (~=0.0.2)
Requires-Dist: click (~=8.1.3)
Requires-Dist: fastapi (~=0.95.0)
Requires-Dist: filetype (~=1.2.0)
Requires-Dist: imagehash (~=4.3.1)
Requires-Dist: numpy (~=1.24.2)
Requires-Dist: onnxruntime (~=1.14.1)
Requires-Dist: opencv-python-headless (~=4.6.0.66)
Requires-Dist: pillow (~=9.3.0)
Requires-Dist: pooch (~=1.6.0)
Requires-Dist: pymatting (~=1.1.8)
Requires-Dist: python-multipart (~=0.0.5)
Requires-Dist: scikit-image (~=0.19.3)
Requires-Dist: scipy (~=1.9.3)
Requires-Dist: tqdm (~=4.65.0)
Requires-Dist: uvicorn (~=0.21.1)
Requires-Dist: watchdog (~=3.0.0)
Provides-Extra: gpu
Requires-Dist: onnxruntime-gpu (~=1.13.1) ; extra == 'gpu'
